LICENSE.rst
MANIFEST.in
README.rst
RELNOTES.rst
setup.cfg
setup.py
generinator_rats/VERSION
generinator_rats/__init__.py
generinator_rats/generate.py
generinator_rats/pkgdata.py
generinator_rats/process.py
generinator_rats.egg-info/PKG-INFO
generinator_rats.egg-info/SOURCES.txt
generinator_rats.egg-info/dependency_links.txt
generinator_rats.egg-info/entry_points.txt
generinator_rats.egg-info/not-zip-safe
generinator_rats.egg-info/requires.txt
generinator_rats.egg-info/top_level.txt
generinator_rats/resources/HTMLLexer.g4
generinator_rats/resources/HTMLParser.g4
generinator_rats/resources/css3.g4