Metadata-Version: 1.0
Name: generinator-rats
Version: 18.2
Summary: Generinator: Random Attributes, Tags & Style
Home-page: https://github.com/renatahodovan/generinator-rats
Author: Renata Hodovan, Akos Kiss
Author-email: hodovan@inf.u-szeged.hu, akiss@inf.u-szeged.hu
License: BSD
Platform: UNKNOWN
